claudetools/__init__.py
claudetools/completion/__init__.py
claudetools/completion/async_complete.py
claudetools/completion/complete.py
claudetools/extract/__init__.py
claudetools/extract/multiple.py
claudetools/extract/single.py
claudetools/prompts/__init__.py
claudetools/prompts/multi_functions.py
claudetools/prompts/single_function.py
claudetools/tools/__init__.py
claudetools/tools/tool.py
tests/__init__.py
tests/test_bedrock.py
tests/test_multiple_function.py
tests/test_single_function.py
tests/test_single_specific.py
claudetools-1.0.3.dist-info/LICENSE
claudetools-1.0.3.dist-info/METADATA
claudetools-1.0.3.dist-info/WHEEL
claudetools-1.0.3.dist-info/top_level.txt
claudetools-1.0.3.dist-info/RECORD
