Metadata-Version: 2.1
Name: claudetools
Version: 1.0.3
Summary: Claudetools is a Python library that enables function calling with the Claude 3 family of language models from Anthropic.
Home-page: https://github.com/vatsalsaglani/claudetools
Author: Vatsal J. Saglani
Author-email: saglanivatsal@gmail.com
Requires-Python: >=3.7
License-File: LICENSE
Requires-Dist: httpx>=0.25.0
Requires-Dist: anthropic>=0.31.0
Requires-Dist: pydantic>=2.4.2
